giftubing/__init__.py
giftubing/main.py
giftubing/creator/__init__.py
giftubing/creator/avatar_creator.py
giftubing/creator/creator_utils/__init__.py
giftubing/creator/creator_utils/read_png.py
giftubing/creator/creator_utils/read_xcf.py
giftubing/creator/creator_utils/resize_choice.py
giftubing/launcher/__init__.py
giftubing/launcher/avatar_launcher.py
giftubing/launcher/utils/__init__.py
giftubing/launcher/utils/facemesher.py
giftubing/launcher/utils/get_face.py
giftubing/launcher/utils/parts.py
giftubing-0.0.2.dist-info/METADATA
giftubing-0.0.2.dist-info/WHEEL
giftubing-0.0.2.dist-info/top_level.txt
giftubing-0.0.2.dist-info/RECORD
