Metadata-Version: 2.1
Name: giftubing
Version: 0.0.2
Summary: frame-based vtubing, create then use avatar
Home-page: https://github.com/CaptainBTeach/giftubing
Author: CaptainBTeach
License: MIT
Classifier: Development Status :: 2 - Pre-Alpha
Classifier: Operating System :: Microsoft :: Windows
Classifier: Environment :: GPU :: NVIDIA CUDA
Classifier: Programming Language :: Python :: 3
Classifier: Programming Language :: Python :: 3.10
Classifier: License :: OSI Approved :: MIT License
Requires-Dist: keyboard
Requires-Dist: hsemotion
Requires-Dist: opencv-python
Requires-Dist: Pillow
Requires-Dist: PySide6
Requires-Dist: mediapipe
Requires-Dist: gimpformats
Requires-Dist: facenet-pytorch
